credstash_envvar_helper/__init__.py
credstash_envvar_helper/credstash_envvar_helper.py
credstash_envvar_helper-0.1.3.dist-info/AUTHORS.rst
credstash_envvar_helper-0.1.3.dist-info/LICENSE
credstash_envvar_helper-0.1.3.dist-info/METADATA
credstash_envvar_helper-0.1.3.dist-info/WHEEL
credstash_envvar_helper-0.1.3.dist-info/top_level.txt
credstash_envvar_helper-0.1.3.dist-info/RECORD
