Metadata-Version: 2.1
Name: credstash-envvar-helper
Version: 0.1.3
Summary: Retrieves secrets from AWS via credstash, and returns a dictionary.
Home-page: https://github.com/knoxilla/credstash_envvar_helper
Author: Thomas Knox
Author-email: knoxilla@gmail.com
License: MIT license
Keywords: credstash_envvar_helper
Platform: UNKNOWN
Classifier: Development Status :: 2 - Pre-Alpha
Classifier: Intended Audience :: Developers
Classifier: License :: OSI Approved :: MIT License
Classifier: Natural Language :: English
Classifier: Programming Language :: Python :: 2
Classifier: Programming Language :: Python :: 2.7
Classifier: Programming Language :: Python :: 3
Classifier: Programming Language :: Python :: 3.5
Classifier: Programming Language :: Python :: 3.6
Classifier: Programming Language :: Python :: 3.7
Classifier: Programming Language :: Python :: 3.8
Requires-Python: >=3.5
Requires-Dist: credstash (>=1.16.1)
